uniconv/__init__.py
uniconv/constants.py
uniconv/converter.py
uniconv-1.0.1.dist-info/licenses/LICENSE
uniconv-1.0.1.dist-info/METADATA
uniconv-1.0.1.dist-info/WHEEL
uniconv-1.0.1.dist-info/top_level.txt
uniconv-1.0.1.dist-info/RECORD
