Metadata-Version: 2.4
Name: uniconv
Version: 1.0.1
Summary: Universal unit converter for engineers
Author-email: Mihanchos <shofer2007@gmail.com>
License-Expression: MIT
Project-URL: Homepage, https://github.com/Misha-Mayskiy/uniconv
Classifier: Programming Language :: Python :: 3
Classifier: Operating System :: OS Independent
Classifier: Topic :: Scientific/Engineering
Requires-Python: >=3.7
License-File: LICENSE
Dynamic: license-file
